certis/__init__.py
certis/base.py
certis/constants.py
certis/core.py
certis/util.py
Certis-0.0.2.dist-info/METADATA
Certis-0.0.2.dist-info/WHEEL
Certis-0.0.2.dist-info/top_level.txt
Certis-0.0.2.dist-info/RECORD
