Metadata-Version: 2.1
Name: Certis
Version: 0.0.2
Summary: Certis, Backtesting For y'all
Home-page: https://github.com/Yeachan-Heo/Certis
Author: Yeachan-Heo
Author-email: rlstart@kakao.com
License: UNKNOWN
Platform: UNKNOWN
Classifier: Programming Language :: Python :: 3
Classifier: License :: OSI Approved :: MIT License
Classifier: Operating System :: OS Independent
Requires-Python: >=3.6
